<?xml version="1.0" encoding="UTF-8"?>

<content-repository style="0.1">
      <repository-id>disa-stig-repo</repository-id>
      <repository-publisher>DISA</repository-publisher>
      <last-updated>2022-04-22T10:51:36</last-updated>
      <license>Open</license>
      <contents>
            <scap-content>
                  <content-id>U_Adobe_Acrobat_Reader_DC_Classic_V2R1_STIG_SCAP_1-2_Benchmark.zip</content-id>
                  <location>https://dl.dod.cyber.mil/wp-content/uploads/stigs/zip/U_Adobe_Acrobat_Reader_DC_Classic_V2R1_STIG_SCAP_1-2_Benchmark.zip</location>
                  <checksum style="SHA512">cda19f68e486d89e35a0227fa5f421e83713d75c6cef539bbdaee95a273d2fdc287c5cf474c51b90f5c33e22e7da64afa8570f1b3521acca52c8b78b9504b80b</checksum>
                  <benchmarks>
                        <benchmark>
                              <benchmark-id>xccdf_mil.disa.stig_benchmark_Adobe_Acrobat_Reader_DC_Classic_Track_STIG</benchmark-id>
                              <title>Adobe Acrobat Reader DC Classic Track Security Technical Implementation Guide</title>
                              <version>002.001</version>
                              <style>SCAP_1.2</style>
                              <status>accepted</status>
                              <status-date>2020-10-23</status-date>
                              <creator>DISA</creator>
                              <publisher>DISA</publisher>
                              <contributor>DISA</contributor>
                              <source>STIG.DOD.MIL</source>
                        </benchmark>
                  </benchmarks>
                  <platforms>
                        <platform>
                              <platform-id style="cpe">cpe:/a:adobe:acrobat_reader_dc:::~~classic~windows~~</platform-id>
                        </platform>
                  </platforms>
            </scap-content>
            <scap-content>
                  <content-id>U_Adobe_Acrobat_Reader_DC_Continuous_V2R1_STIG_SCAP_1-2_Benchmark.zip</content-id>
                  <location>https://dl.dod.cyber.mil/wp-content/uploads/stigs/zip/U_Adobe_Acrobat_Reader_DC_Continuous_V2R1_STIG_SCAP_1-2_Benchmark.zip</location>
                  <checksum style="SHA512">afc36dc5ed85545f19c51e6c8e18a2ae1e9115c8285d3fea5f9fae2caa82026f8b1f0d732eca1962088f02f84574f8358f49279b230138123dbe968807bbc0b7</checksum>
                  <benchmarks>
                        <benchmark>
                              <benchmark-id>xccdf_mil.disa.stig_benchmark_Adobe_Acrobat_Reader_DC_Continuous_Track_STIG</benchmark-id>
                              <title>Adobe Acrobat Reader DC Continuous Track Security Technical Implementation Guide</title>
                              <version>002.001</version>
                              <style>SCAP_1.2</style>
                              <status>accepted</status>
                              <status-date>2021-06-22</status-date>
                              <creator>DISA</creator>
                              <publisher>DISA</publisher>
                              <contributor>DISA</contributor>
                              <source>STIG.DOD.MIL</source>
                        </benchmark>
                  </benchmarks>
                  <platforms>
                        <platform>
                              <platform-id style="cpe">cpe:/a:adobe:acrobat_reader_dc:::~~continuous~windows~~</platform-id>
                        </platform>
                  </platforms>
            </scap-content>
            <scap-content>
                  <content-id>U_CAN_Ubuntu_18-04_V2R6_STIG_SCAP_1-2_Benchmark.zip</content-id>
                  <location>https://dl.dod.cyber.mil/wp-content/uploads/stigs/zip/U_CAN_Ubuntu_18-04_V2R6_STIG_SCAP_1-2_Benchmark.zip</location>
                  <checksum style="SHA512">c91945f684954a3cb433bf3b1ca0371d2ff1ef185a77fe47d4bac1258cfd9367b8c88080af60f5059a7970c4aa3427c7db4cec0d601cf9229fe820dd76d18e9a</checksum>
                  <benchmarks>
                        <benchmark>
                              <benchmark-id>xccdf_mil.disa.stig_benchmark_CAN_Ubuntu_18-04_STIG</benchmark-id>
                              <title>Canonical Ubuntu 18.04 LTS Security Technical Implementation Guide</title>
                              <version>002.006</version>
                              <style>SCAP_1.2</style>
                              <status>accepted</status>
                              <status-date>2022-02-17</status-date>
                              <creator>DISA</creator>
                              <publisher>DISA</publisher>
                              <contributor>DISA</contributor>
                              <source>STIG.DOD.MIL</source>
                        </benchmark>
                  </benchmarks>
                  <platforms>
                        <platform>
                              <platform-id style="cpe">cpe:/o:canonical:ubuntu_linux:18.04</platform-id>
                        </platform>
                  </platforms>
            </scap-content>
            <scap-content>
                  <content-id>U_CAN_Ubuntu_20-04_LTS_V1R2_STIG_SCAP_1-2_Benchmark.zip</content-id>
                  <location>https://dl.dod.cyber.mil/wp-content/uploads/stigs/zip/U_CAN_Ubuntu_20-04_LTS_V1R2_STIG_SCAP_1-2_Benchmark.zip</location>
                  <checksum style="SHA512">31315ec3792282f8cdea4ab38fe084d112af0034e60203de46d414b61cff498a1335271e9a32132ce627cd088d24d923378c44804f51423942ffc7bdba28ffc5</checksum>
                  <benchmarks>
                        <benchmark>
                              <benchmark-id>xccdf_mil.disa.stig_benchmark_Canonical_Ubuntu_20-04_LTS_STIG</benchmark-id>
                              <title>Canonical Ubuntu 20.04 LTS Security Technical Implementation Guide</title>
                              <version>001.002</version>
                              <style>SCAP_1.2</style>
                              <status>accepted</status>
                              <status-date>2022-02-17</status-date>
                              <creator>DISA</creator>
                              <publisher>DISA</publisher>
                              <contributor>DISA</contributor>
                              <source>STIG.DOD.MIL</source>
                        </benchmark>
                  </benchmarks>
                  <platforms>
                        <platform>
                              <platform-id style="cpe">cpe:/o:canonical:ubuntu_linux:20.04</platform-id>
                        </platform>
                  </platforms>
            </scap-content>
            <scap-content>
                  <content-id>U_Cisco_IOS-XE_Router_NDM_V1R3_STIG_SCAP_1-3_Benchmark.zip</content-id>
                  <location>https://dl.dod.cyber.mil/wp-content/uploads/stigs/zip/U_Cisco_IOS-XE_Router_NDM_V1R3_STIG_SCAP_1-3_Benchmark.zip</location>
                  <checksum style="SHA512">c8417f255b7130a0617f2fad2b56c32c2de96afee6a85be7dc87d81900084684cda15d220976b8a2bee0583b601ec9899c22a5797b528f8f940c31a324c2c1eb</checksum>
                  <benchmarks>
                        <benchmark>
                              <benchmark-id>xccdf_mil.disa.stig_benchmark_Cisco_IOS-XE_Router_NDM_STIG</benchmark-id>
                              <title>Cisco IOS XE Router NDM Security Technical Implementation Guide</title>
                              <version>001.003</version>
                              <style>SCAP_1.3</style>
                              <status>accepted</status>
                              <status-date>2021-09-22</status-date>
                              <creator>DISA</creator>
                              <publisher>DISA</publisher>
                              <contributor>DISA</contributor>
                              <source>STIG.DOD.MIL</source>
                        </benchmark>
                  </benchmarks>
                  <platforms>
                        <platform>
                              <platform-id style="cpe">cpe:/o:cisco:ios_xe:-</platform-id>
                        </platform>
                  </platforms>
            </scap-content>
            <scap-content>
                  <content-id>U_Cisco_IOS-XE_Router_RTR_V1R1_STIG_SCAP_1-3_Benchmark.zip</content-id>
                  <location>https://dl.dod.cyber.mil/wp-content/uploads/stigs/zip/U_Cisco_IOS-XE_Router_RTR_V1R1_STIG_SCAP_1-3_Benchmark.zip</location>
                  <checksum style="SHA512">777c9f6dc088e7df18401cadd99de221ab2ef6a11aed2bd1753e6e47261a044320cc2d44b7ccc75995a68268bf3b3fa1c43efb9102bf26724d8777b70cbae616</checksum>
                  <benchmarks>
                        <benchmark>
                              <benchmark-id>xccdf_mil.disa.stig_benchmark_Cisco_IOS-XE_Router_RTR_STIG</benchmark-id>
                              <title>Cisco IOS XE Router RTR Security Technical Implementation Guide</title>
                              <version>001.001</version>
                              <style>SCAP_1.3</style>
                              <status>accepted</status>
                              <status-date>2021-03-26</status-date>
                              <creator>DISA</creator>
                              <publisher>DISA</publisher>
                              <contributor>DISA</contributor>
                              <source>STIG.DOD.MIL</source>
                        </benchmark>
                  </benchmarks>
                  <platforms>
                        <platform>
                              <platform-id style="cpe">cpe:/o:cisco:ios_xe:-</platform-id>
                        </platform>
                  </platforms>
            </scap-content>
            <scap-content>
                  <content-id>U_Google_Chrome_V2R6_STIG_SCAP_1-2_Benchmark.zip</content-id>
                  <location>https://dl.dod.cyber.mil/wp-content/uploads/stigs/zip/U_Google_Chrome_V2R6_STIG_SCAP_1-2_Benchmark.zip</location>
                  <checksum style="SHA512">c3f4b04bc66003eb58e81d467615c1a2297ef667133605879b5a09a0de31ef28bc5307d8eb9e1e07317c2a735ddf8fbc983c278270867babf6b3f3e2c1f368a0</checksum>
                  <benchmarks>
                        <benchmark>
                              <benchmark-id>xccdf_mil.disa.stig_benchmark_Google_Chrome_Current_Windows</benchmark-id>
                              <title>Google Chrome Current Windows Security Technical Implementation Guide</title>
                              <version>002.006</version>
                              <style>SCAP_1.2</style>
                              <status>accepted</status>
                              <status-date>2022-03-02</status-date>
                              <creator>DISA</creator>
                              <publisher>DISA</publisher>
                              <contributor>DISA</contributor>
                              <source>STIG.DOD.MIL</source>
                        </benchmark>
                  </benchmarks>
                  <platforms>
                        <platform>
                              <platform-id style="cpe">cpe:/a:google:chrome</platform-id>
                        </platform>
                  </platforms>
            </scap-content>
            <scap-content>
                  <content-id>U_MS_DotNet_Framework_4-0_V2R1_STIG_SCAP_1-2_Benchmark.zip</content-id>
                  <location>https://dl.dod.cyber.mil/wp-content/uploads/stigs/zip/U_MS_DotNet_Framework_4-0_V2R1_STIG_SCAP_1-2_Benchmark.zip</location>
                  <checksum style="SHA512">b7f37452341e3db58aae63ea9ed975cac4ab3036c254fdd7b86958251cd300a25210bb4e18a3996adf39fe7d9acdd3904d6b71298cf2a896ef8ae32ae84e686b</checksum>
                  <benchmarks>
                        <benchmark>
                              <benchmark-id>xccdf_mil.disa.stig_benchmark_MS_Dot_Net_Framework</benchmark-id>
                              <title>Microsoft DotNet Framework 4.0 Security Technical Implementation Guide</title>
                              <version>002.001</version>
                              <style>SCAP_1.2</style>
                              <status>accepted</status>
                              <status-date>2020-12-11</status-date>
                              <creator>DISA</creator>
                              <publisher>DISA</publisher>
                              <contributor>DISA</contributor>
                              <source>STIG.DOD.MIL</source>
                        </benchmark>
                  </benchmarks>
                  <platforms>
                        <platform>
                              <platform-id style="cpe">cpe:/a:microsoft:.net_framework:4.0</platform-id>
                        </platform>
                  </platforms>
            </scap-content>
            <scap-content>
                  <content-id>U_MS_Edge_V1R1_STIG_SCAP_1-2_Benchmark.zip</content-id>
                  <location>https://dl.dod.cyber.mil/wp-content/uploads/stigs/zip/U_MS_Edge_V1R1_STIG_SCAP_1-2_Benchmark.zip</location>
                  <checksum style="SHA512">9b9893fd86761e26714f05db394c17bc2ae974a86107e2086dd0e27475920ef739990192be6056bd18418582aad7592e305ff571c074df10648d9a800e884db2</checksum>
                  <benchmarks>
                        <benchmark>
                              <benchmark-id>xccdf_mil.disa.stig_benchmark_MS_Edge_STIG</benchmark-id>
                              <title>Microsoft Edge Security Technical Implementation Guide</title>
                              <version>001.001</version>
                              <style>SCAP_1.2</style>
                              <status>accepted</status>
                              <status-date>2021-09-03</status-date>
                              <creator>DISA</creator>
                              <publisher>DISA</publisher>
                              <contributor>DISA</contributor>
                              <source>STIG.DOD.MIL</source>
                        </benchmark>
                  </benchmarks>
                  <platforms>
                        <platform>
                              <platform-id style="cpe">cpe:/a:microsoft:edge</platform-id>
                        </platform>
                  </platforms>
            </scap-content>
            <scap-content>
                  <content-id>U_MS_IE11_V2R1_STIG_SCAP_1-2_Benchmark.zip</content-id>
                  <location>https://dl.dod.cyber.mil/wp-content/uploads/stigs/zip/U_MS_IE11_V2R1_STIG_SCAP_1-2_Benchmark.zip</location>
                  <checksum style="SHA512">d663712a0c62373bb8ece5dacba28a1c08f7beefbc2b7b19ac704232e921eb4e283ed226ad8e4ab2eebc02ba24bf7df78079d1777e75af4ec2760d708dcfb2ca</checksum>
                  <benchmarks>
                        <benchmark>
                              <benchmark-id>xccdf_mil.disa.stig_benchmark_IE_11_STIG</benchmark-id>
                              <title>Microsoft Internet Explorer 11 Security Technical Implementation Guide</title>
                              <version>002.001</version>
                              <style>SCAP_1.2</style>
                              <status>accepted</status>
                              <status-date>2021-10-12</status-date>
                              <creator>DISA</creator>
                              <publisher>DISA</publisher>
                              <contributor>DISA</contributor>
                              <source>STIG.DOD.MIL</source>
                        </benchmark>
                  </benchmarks>
                  <platforms>
                        <platform>
                              <platform-id style="cpe">cpe:/a:microsoft:internet_explorer:11</platform-id>
                        </platform>
                  </platforms>
            </scap-content>
            <scap-content>
                  <content-id>U_MS_Windows_10_V2R3_STIG_SCAP_1-2_Benchmark.zip</content-id>
                  <location>https://dl.dod.cyber.mil/wp-content/uploads/stigs/zip/U_MS_Windows_10_V2R3_STIG_SCAP_1-2_Benchmark.zip</location>
                  <checksum style="SHA512">804aec16a0fa2b2a79427d18e83e23655749d508f61bf5e3243a6de68beee34ccd69b7507b622937f6ab7aae9f9712c640970648237f2a556483dde905a9af01</checksum>
                  <benchmarks>
                        <benchmark>
                              <benchmark-id>xccdf_mil.disa.stig_benchmark_Windows_10_STIG</benchmark-id>
                              <title>Windows 10 Security Technical Implementation Guide</title>
                              <version>002.003</version>
                              <style>SCAP_1.2</style>
                              <status>accepted</status>
                              <status-date>2021-08-18</status-date>
                              <creator>DISA</creator>
                              <publisher>DISA</publisher>
                              <contributor>DISA</contributor>
                              <source>STIG.DOD.MIL</source>
                        </benchmark>
                  </benchmarks>
                  <platforms>
                        <platform>
                              <platform-id style="cpe">cpe:/o:microsoft:windows_10</platform-id>
                        </platform>
                  </platforms>
            </scap-content>
            <scap-content>
                  <content-id>U_MS_Windows_2012_and_2012_R2_DC_V3R2_STIG_SCAP_1-2_Benchmark.zip</content-id>
                  <location>https://dl.dod.cyber.mil/wp-content/uploads/stigs/zip/U_MS_Windows_2012_and_2012_R2_DC_V3R2_STIG_SCAP_1-2_Benchmark.zip</location>
                  <checksum style="SHA512">6a84b77199cf3b3c2e387b041783e66412fc7150434c3f1905fcd20265fe222fe7d7cedcf51a19069cff057a5b3cc7085b8bebaf6259f89ec01e53f2dfab0fc5</checksum>
                  <benchmarks>
                        <benchmark>
                              <benchmark-id>xccdf_mil.disa.stig_benchmark_Windows_2012_DC_STIG</benchmark-id>
                              <title>Microsoft Windows Server 2012/2012 R2 Domain Controller Security Technical Implementation Guide</title>
                              <version>003.002</version>
                              <style>SCAP_1.2</style>
                              <status>accepted</status>
                              <status-date>2021-10-18</status-date>
                              <creator>DISA</creator>
                              <publisher>DISA</publisher>
                              <contributor>DISA</contributor>
                              <source>STIG.DOD.MIL</source>
                        </benchmark>
                  </benchmarks>
                  <platforms>
                        <platform>
                              <platform-id style="cpe">cpe:/o:microsoft:windows_server_2012:-</platform-id>
                        </platform>
                        <platform>
                              <platform-id style="cpe">cpe:/o:microsoft:windows_server_2012:r2</platform-id>
                        </platform>
                  </platforms>
            </scap-content>
            <scap-content>
                  <content-id>U_MS_Windows_2012_and_2012_R2_MS_V3R2_STIG_SCAP_1-2_Benchmark.zip</content-id>
                  <location>https://dl.dod.cyber.mil/wp-content/uploads/stigs/zip/U_MS_Windows_2012_and_2012_R2_MS_V3R2_STIG_SCAP_1-2_Benchmark.zip</location>
                  <checksum style="SHA512">7941e2dd6ea806ece1eb7935b6f8f3175c693ee575d29f313c5e5a3ba262391875f09d9bf7c7bba220041a870b369594765eea28911a1dc992e3589b6acef76d</checksum>
                  <benchmarks>
                        <benchmark>
                              <benchmark-id>xccdf_mil.disa.stig_benchmark_Windows_2012_MS_STIG</benchmark-id>
                              <title>Microsoft Windows Server 2012/2012 R2 Member Server Security Technical Implementation Guide</title>
                              <version>003.002</version>
                              <style>SCAP_1.2</style>
                              <status>accepted</status>
                              <status-date>2021-10-18</status-date>
                              <creator>DISA</creator>
                              <publisher>DISA</publisher>
                              <contributor>DISA</contributor>
                              <source>STIG.DOD.MIL</source>
                        </benchmark>
                  </benchmarks>
                  <platforms>
                        <platform>
                              <platform-id style="cpe">cpe:/o:microsoft:windows_server_2012:r2</platform-id>
                        </platform>
                        <platform>
                              <platform-id style="cpe">cpe:/o:microsoft:windows_server_2012:-</platform-id>
                        </platform>
                  </platforms>
            </scap-content>
            <scap-content>
                  <content-id>U_MS_Windows_Defender_AV_V2R2_STIG_SCAP_1-2_Benchmark.zip</content-id>
                  <location>https://dl.dod.cyber.mil/wp-content/uploads/stigs/zip/U_MS_Windows_Defender_AV_V2R2_STIG_SCAP_1-2_Benchmark.zip</location>
                  <checksum style="SHA512">158f38ddae760138143d508c71252d04021068f109d628cd2a7465b017255929935864010ef207b94bcfab1a188fdf748128f3bdd9971790f56e33e1a3a63886</checksum>
                  <benchmarks>
                        <benchmark>
                              <benchmark-id>xccdf_mil.disa.stig_benchmark_Windows_Defender_Antivirus</benchmark-id>
                              <title>Microsoft Windows Defender Antivirus Security Technical Implementation Guide</title>
                              <version>002.002</version>
                              <style>SCAP_1.2</style>
                              <status>accepted</status>
                              <status-date>2021-09-30</status-date>
                              <creator>DISA</creator>
                              <publisher>DISA</publisher>
                              <contributor>DISA</contributor>
                              <source>STIG.DOD.MIL</source>
                        </benchmark>
                  </benchmarks>
                  <platforms>
                        <platform>
                              <platform-id style="cpe">cpe:/a:microsoft:windows_defender</platform-id>
                        </platform>
                  </platforms>
            </scap-content>
            <scap-content>
                  <content-id>U_MS_Windows_Firewall_V2R1_STIG_SCAP_1-2_Benchmark.zip</content-id>
                  <location>https://dl.dod.cyber.mil/wp-content/uploads/stigs/zip/U_MS_Windows_Firewall_V2R1_STIG_SCAP_1-2_Benchmark.zip</location>
                  <checksum style="SHA512">64fd57131880b276a3c76bea4435cda31318be0d1f72e3ee01836420b6b0ed173780182f2fd99f3831c45bcef220f3ddf59e3c13a58984920858cc5f5b680751</checksum>
                  <benchmarks>
                        <benchmark>
                              <benchmark-id>xccdf_mil.disa.stig_benchmark_Windows_Firewall_with_Advanced_Security</benchmark-id>
                              <title>Windows Firewall with Advanced Security Security Technical Implementation Guide</title>
                              <version>002.001</version>
                              <style>SCAP_1.2</style>
                              <status>accepted</status>
                              <status-date>2021-10-15</status-date>
                              <creator>DISA</creator>
                              <publisher>DISA</publisher>
                              <contributor>DISA</contributor>
                              <source>STIG.DOD.MIL</source>
                        </benchmark>
                  </benchmarks>
                  <platforms>
                        <platform>
                              <platform-id style="cpe">cpe:/o:microsoft:windows_8.1</platform-id>
                        </platform>
                        <platform>
                              <platform-id style="cpe">cpe:/o:microsoft:windows_server_2008</platform-id>
                        </platform>
                        <platform>
                              <platform-id style="cpe">cpe:/o:microsoft:windows_server_2008:r2</platform-id>
                        </platform>
                        <platform>
                              <platform-id style="cpe">cpe:/o:microsoft:windows_7</platform-id>
                        </platform>
                        <platform>
                              <platform-id style="cpe">cpe:/o:microsoft:windows_server_2016:-</platform-id>
                        </platform>
                        <platform>
                              <platform-id style="cpe">cpe:/o:microsoft:windows_10</platform-id>
                        </platform>
                        <platform>
                              <platform-id style="cpe">cpe:/o:microsoft:windows_server_2012:-</platform-id>
                        </platform>
                        <platform>
                              <platform-id style="cpe">cpe:/o:microsoft:windows_server_2019:-</platform-id>
                        </platform>
                        <platform>
                              <platform-id style="cpe">cpe:/o:microsoft:windows_8</platform-id>
                        </platform>
                        <platform>
                              <platform-id style="cpe">cpe:/o:microsoft:windows_vista</platform-id>
                        </platform>
                        <platform>
                              <platform-id style="cpe">cpe:/o:microsoft:windows_server_2012:r2</platform-id>
                        </platform>
                  </platforms>
            </scap-content>
            <scap-content>
                  <content-id>U_MS_Windows_Server_2016_V2R1_STIG_SCAP_1-2_Benchmark.zip</content-id>
                  <location>https://dl.dod.cyber.mil/wp-content/uploads/stigs/zip/U_MS_Windows_Server_2016_V2R1_STIG_SCAP_1-2_Benchmark.zip</location>
                  <checksum style="SHA512">5b9bd6f95c95ad6ec1e0e9ea22f129be3f5600dbee5cba2efe54d9b12992d453fb29d76672656d405ce8bf5b24486ebb479945c73797ef331a60221533b84379</checksum>
                  <benchmarks>
                        <benchmark>
                              <benchmark-id>xccdf_mil.disa.stig_benchmark_Windows_Server_2016_STIG</benchmark-id>
                              <title>Microsoft Windows Server 2016 Security Technical Implementation Guide</title>
                              <version>002.001</version>
                              <style>SCAP_1.2</style>
                              <status>accepted</status>
                              <status-date>2020-10-15</status-date>
                              <creator>DISA</creator>
                              <publisher>DISA</publisher>
                              <contributor>DISA</contributor>
                              <source>STIG.DOD.MIL</source>
                        </benchmark>
                  </benchmarks>
                  <platforms>
                        <platform>
                              <platform-id style="cpe">cpe:/o:microsoft:windows_server_2016:-</platform-id>
                        </platform>
                  </platforms>
            </scap-content>
            <scap-content>
                  <content-id>U_MS_Windows_Server_2019_V2R1_STIG_SCAP_1-2_Benchmark.zip</content-id>
                  <location>https://dl.dod.cyber.mil/wp-content/uploads/stigs/zip/U_MS_Windows_Server_2019_V2R1_STIG_SCAP_1-2_Benchmark.zip</location>
                  <checksum style="SHA512">551d395236409c01b62801826e11353e9475043e2e88ad919013b0d919f88aec0ce87602faabc47d6a61db218705656ebc8f7cfbb2a9224b9c18b6756c6804e0</checksum>
                  <benchmarks>
                        <benchmark>
                              <benchmark-id>xccdf_mil.disa.stig_benchmark_Windows_Server_2019_STIG</benchmark-id>
                              <title>Microsoft Windows Server 2019 Security Technical Implementation Guide</title>
                              <version>002.001</version>
                              <style>SCAP_1.2</style>
                              <status>accepted</status>
                              <status-date>2020-10-26</status-date>
                              <creator>DISA</creator>
                              <publisher>DISA</publisher>
                              <contributor>DISA</contributor>
                              <source>STIG.DOD.MIL</source>
                        </benchmark>
                  </benchmarks>
                  <platforms>
                        <platform>
                              <platform-id style="cpe">cpe:/o:microsoft:windows_server_2019:-</platform-id>
                        </platform>
                  </platforms>
            </scap-content>
            <scap-content>
                  <content-id>U_Oracle_Linux_7_V2R7_STIG_SCAP_1-2_Benchmark.zip</content-id>
                  <location>https://dl.dod.cyber.mil/wp-content/uploads/stigs/zip/U_Oracle_Linux_7_V2R7_STIG_SCAP_1-2_Benchmark.zip</location>
                  <checksum style="SHA512">5b170847902017ca02af265749720ab77ca75521b46aa77ade6859d7c95cda274b76976b7ced9c5ce19eba70166e7d7d13f821ceebd800e6eb8ea67ec3053384</checksum>
                  <benchmarks>
                        <benchmark>
                              <benchmark-id>xccdf_mil.disa.stig_benchmark_Oracle_Linux_7_STIG</benchmark-id>
                              <title>Oracle Linux 7 Security Technical Implementation Guide</title>
                              <version>002.007</version>
                              <style>SCAP_1.2</style>
                              <status>accepted</status>
                              <status-date>2022-02-11</status-date>
                              <creator>DISA</creator>
                              <publisher>DISA</publisher>
                              <contributor>DISA</contributor>
                              <source>STIG.DOD.MIL</source>
                        </benchmark>
                  </benchmarks>
                  <platforms>
                        <platform>
                              <platform-id style="cpe">cpe:/o:oracle:linux:7</platform-id>
                        </platform>
                  </platforms>
            </scap-content>
            <scap-content>
                  <content-id>U_RHEL_7_V3R6_STIG_SCAP_1-2_Benchmark.zip</content-id>
                  <location>https://dl.dod.cyber.mil/wp-content/uploads/stigs/zip/U_RHEL_7_V3R6_STIG_SCAP_1-2_Benchmark.zip</location>
                  <checksum style="SHA512">8fc100a581ea2ad067e95cd924f481fdfa827b0c0bc0e496ba5537d6013620d1dd66e92c36902379ebf1fadf33458c4f216829aba7558dfc4b475ed63c4129ca</checksum>
                  <benchmarks>
                        <benchmark>
                              <benchmark-id>xccdf_mil.disa.stig_benchmark_RHEL_7_STIG</benchmark-id>
                              <title>Red Hat Enterprise Linux 7 Security Technical Implementation Guide</title>
                              <version>003.006</version>
                              <style>SCAP_1.2</style>
                              <status>accepted</status>
                              <status-date>2021-12-02</status-date>
                              <creator>DISA</creator>
                              <publisher>DISA</publisher>
                              <contributor>DISA</contributor>
                              <source>STIG.DOD.MIL</source>
                        </benchmark>
                  </benchmarks>
                  <platforms>
                        <platform>
                              <platform-id style="cpe">cpe:/o:redhat:enterprise_linux:7</platform-id>
                        </platform>
                  </platforms>
            </scap-content>
            <scap-content>
                  <content-id>U_RHEL_7_V3R7_STIG_SCAP_1-2_Benchmark.zip</content-id>
                  <location>https://dl.dod.cyber.mil/wp-content/uploads/stigs/zip/U_RHEL_7_V3R7_STIG_SCAP_1-2_Benchmark.zip</location>
                  <checksum style="SHA512">f596060a494d036c35a7fff398d608321031d6f5700dd425054ef7c74a811a9df0beae67385cca207242b03075d0ff05e408fec18299e8786975376c2c84d01f</checksum>
                  <benchmarks>
                        <benchmark>
                              <benchmark-id>xccdf_mil.disa.stig_benchmark_RHEL_7_STIG</benchmark-id>
                              <title>Red Hat Enterprise Linux 7 Security Technical Implementation Guide</title>
                              <version>003.007</version>
                              <style>SCAP_1.2</style>
                              <status>accepted</status>
                              <status-date>2022-02-17</status-date>
                              <creator>DISA</creator>
                              <publisher>DISA</publisher>
                              <contributor>DISA</contributor>
                              <source>STIG.DOD.MIL</source>
                        </benchmark>
                  </benchmarks>
                  <platforms>
                        <platform>
                              <platform-id style="cpe">cpe:/o:redhat:enterprise_linux:7</platform-id>
                        </platform>
                  </platforms>
            </scap-content>
            <scap-content>
                  <content-id>U_RHEL_8_V1R5_STIG_SCAP_1-2_Benchmark.zip</content-id>
                  <location>https://dl.dod.cyber.mil/wp-content/uploads/stigs/zip/U_RHEL_8_V1R5_STIG_SCAP_1-2_Benchmark.zip</location>
                  <checksum style="SHA512">03047502385c85029e77c540018b9b8ff0b58f7830d45ca8ce3baceb5ae212e05039dbacba36f6e7367609fc2617fc7f1efe99ce053981ff50d0cd1339913d34</checksum>
                  <benchmarks>
                        <benchmark>
                              <benchmark-id>xccdf_mil.disa.stig_benchmark_RHEL_8_STIG</benchmark-id>
                              <title>Red Hat Enterprise Linux 8 Security Technical Implementation Guide</title>
                              <version>001.005</version>
                              <style>SCAP_1.2</style>
                              <status>accepted</status>
                              <status-date>2022-02-17</status-date>
                              <creator>DISA</creator>
                              <publisher>DISA</publisher>
                              <contributor>DISA</contributor>
                              <source>STIG.DOD.MIL</source>
                        </benchmark>
                  </benchmarks>
                  <platforms>
                        <platform>
                              <platform-id style="cpe">cpe:/o:redhat:enterprise_linux:8</platform-id>
                        </platform>
                  </platforms>
            </scap-content>
            <scap-content>
                  <content-id>U_SLES_12_V2R6_STIG_SCAP_1-2_Benchmark.zip</content-id>
                  <location>https://dl.dod.cyber.mil/wp-content/uploads/stigs/zip/U_SLES_12_V2R6_STIG_SCAP_1-2_Benchmark.zip</location>
                  <checksum style="SHA512">2a8c58f3957742d0cdc907d7f82df569b62106fdf564eaf2e6d7aaf52a33222e65ca9811b8379ac66c44aba0ab29261862131dd633f91b781f3ddbf5da55abfc</checksum>
                  <benchmarks>
                        <benchmark>
                              <benchmark-id>xccdf_mil.disa.stig_benchmark_SLES_12_STIG</benchmark-id>
                              <title>SLES 12 Security Technical Implementation Guide</title>
                              <version>002.006</version>
                              <style>SCAP_1.2</style>
                              <status>accepted</status>
                              <status-date>2021-11-30</status-date>
                              <creator>DISA</creator>
                              <publisher>DISA</publisher>
                              <contributor>DISA</contributor>
                              <source>STIG.DOD.MIL</source>
                        </benchmark>
                  </benchmarks>
                  <platforms>
                        <platform>
                              <platform-id style="cpe">cpe:/o:suse:suse_enterprise_linux_server:12</platform-id>
                        </platform>
                  </platforms>
            </scap-content>
            <scap-content>
                  <content-id>U_SLES_15_V1R1_STIG_SCAP_1-2_Benchmark.zip</content-id>
                  <location>https://dl.dod.cyber.mil/wp-content/uploads/stigs/zip/U_SLES_15_V1R1_STIG_SCAP_1-2_Benchmark.zip</location>
                  <checksum style="SHA512">bdda6885fcceea5ea7189d1f28c59d36539a9d84fdc700a59613a3b34209de1c4cfb2affa2f749893cbaf31f982fd380f7f12ec3765da6d2377532d92e872c65</checksum>
                  <benchmarks>
                        <benchmark>
                              <benchmark-id>xccdf_mil.disa.stig_benchmark_SLES_15_STIG</benchmark-id>
                              <title>SUSE Linux Enterprise Server 15 Security Technical Implementation Guide</title>
                              <version>001.001</version>
                              <style>SCAP_1.2</style>
                              <status>accepted</status>
                              <status-date>2021-11-30</status-date>
                              <creator>DISA</creator>
                              <publisher>DISA</publisher>
                              <contributor>DISA</contributor>
                              <source>STIG.DOD.MIL</source>
                        </benchmark>
                  </benchmarks>
                  <platforms>
                        <platform>
                              <platform-id style="cpe">cpe:/o:suse:suse_enterprise_linux_server:15</platform-id>
                        </platform>
                  </platforms>
            </scap-content>
            <scap-content>
                  <content-id>U_SOL_10_SPARC_V2R2_STIG_SCAP_1-2_Benchmark.zip</content-id>
                  <location>https://dl.dod.cyber.mil/wp-content/uploads/stigs/zip/U_SOL_10_SPARC_V2R2_STIG_SCAP_1-2_Benchmark.zip</location>
                  <checksum style="SHA512">61a7c413dd756dd096ce0136509c7333013db79a1cac48158dcc6851c2311f2db922118a91c7a2e5652c805b73120747766b9c96952d52281519b19ab3021d98</checksum>
                  <benchmarks>
                        <benchmark>
                              <benchmark-id>xccdf_mil.disa.stig_benchmark_Solaris_10_SPARC_STIG</benchmark-id>
                              <title>Solaris 10 SPARC Security Technical Implementation Guide</title>
                              <version>002.002</version>
                              <style>SCAP_1.2</style>
                              <status>accepted</status>
                              <status-date>2020-12-04</status-date>
                              <creator>DISA</creator>
                              <publisher>DISA</publisher>
                              <contributor>DISA</contributor>
                              <source>STIG.DOD.MIL</source>
                        </benchmark>
                  </benchmarks>
                  <platforms>
                        <platform>
                              <platform-id style="cpe">cpe:/o:sun:sunos:5.10:-:sparc</platform-id>
                        </platform>
                  </platforms>
            </scap-content>
            <scap-content>
                  <content-id>U_SOL_10_X86_V2R2_STIG_SCAP_1-2_Benchmark.zip</content-id>
                  <location>https://dl.dod.cyber.mil/wp-content/uploads/stigs/zip/U_SOL_10_X86_V2R2_STIG_SCAP_1-2_Benchmark.zip</location>
                  <checksum style="SHA512">a8ced422369e4b5bb5ecbf613d39f33b122ba23f1cea19ffea26538272f88f80611136b05f7b510e895f660ff35996c45d2847894a4935cd107ee20752b80268</checksum>
                  <benchmarks>
                        <benchmark>
                              <benchmark-id>xccdf_mil.disa.stig_benchmark_Solaris_10_X86_STIG</benchmark-id>
                              <title>Solaris 10 X86 Security Technical Implementation Guide</title>
                              <version>002.002</version>
                              <style>SCAP_1.2</style>
                              <status>accepted</status>
                              <status-date>2020-12-04</status-date>
                              <creator>DISA</creator>
                              <publisher>DISA</publisher>
                              <contributor>DISA</contributor>
                              <source>STIG.DOD.MIL</source>
                        </benchmark>
                  </benchmarks>
                  <platforms>
                        <platform>
                              <platform-id style="cpe">cpe:/o:sun:sunos:5.10:-:ix86</platform-id>
                        </platform>
                  </platforms>
            </scap-content>
            <scap-content>
                  <content-id>U_SOL_11_SPARC_V2R3_STIG_SCAP_1-2_Benchmark.zip</content-id>
                  <location>https://dl.dod.cyber.mil/wp-content/uploads/stigs/zip/U_SOL_11_SPARC_V2R3_STIG_SCAP_1-2_Benchmark.zip</location>
                  <checksum style="SHA512">46c486c0d1489f744cfdc92ac961e4d13fd2f8665291804617738460f60a5780822409d0f6cc83306c9ba578266af6494f54677fc34f8e9154dd4fc04373d599</checksum>
                  <benchmarks>
                        <benchmark>
                              <benchmark-id>xccdf_mil.disa.stig_benchmark_Solaris_11_SPARC_STIG</benchmark-id>
                              <title>Solaris 11 SPARC Security Technical Implementation Guide</title>
                              <version>002.003</version>
                              <style>SCAP_1.2</style>
                              <status>accepted</status>
                              <status-date>2021-11-23</status-date>
                              <creator>DISA</creator>
                              <publisher>DISA</publisher>
                              <contributor>DISA</contributor>
                              <source>STIG.DOD.MIL</source>
                        </benchmark>
                  </benchmarks>
                  <platforms>
                        <platform>
                              <platform-id style="cpe">cpe:/o:sun:sunos:5.11:-:~~~~sparc~</platform-id>
                        </platform>
                  </platforms>
            </scap-content>
            <scap-content>
                  <content-id>U_SOL_11_X86_V2R3_STIG_SCAP_1-2_Benchmark.zip</content-id>
                  <location>https://dl.dod.cyber.mil/wp-content/uploads/stigs/zip/U_SOL_11_X86_V2R3_STIG_SCAP_1-2_Benchmark.zip</location>
                  <checksum style="SHA512">3574143893b19e8aab3e6a13aab904ebb908580c2366118256840d8255d2567369fcb764ba79830fbf7622f47f62d0e6734d906d0fb662cbc94dfe18f06691c5</checksum>
                  <benchmarks>
                        <benchmark>
                              <benchmark-id>xccdf_mil.disa.stig_benchmark_Solaris_11_X86_STIG</benchmark-id>
                              <title>Solaris 11 X86 Security Technical Implementation Guide</title>
                              <version>002.003</version>
                              <style>SCAP_1.2</style>
                              <status>accepted</status>
                              <status-date>2021-11-23</status-date>
                              <creator>DISA</creator>
                              <publisher>DISA</publisher>
                              <contributor>DISA</contributor>
                              <source>STIG.DOD.MIL</source>
                        </benchmark>
                  </benchmarks>
                  <platforms>
                        <platform>
                              <platform-id style="cpe">cpe:/o:sun:sunos:5.11:-:~~~~x86~</platform-id>
                        </platform>
                  </platforms>
            </scap-content>
      </contents>
</content-repository>
